getsecret/__init__.py
getsecret-0.0.6.dist-info/METADATA
getsecret-0.0.6.dist-info/WHEEL
getsecret-0.0.6.dist-info/top_level.txt
getsecret-0.0.6.dist-info/RECORD
