Metadata-Version: 2.1
Name: getsecret
Version: 0.0.6
Summary: Reads credentials from a yaml file
Home-page: https://github.com/gkovacs/python-getsecret
Author: Geza Kovacs
Author-email: noreply@gkovacs.com
License: UNKNOWN
Platform: UNKNOWN
Classifier: Programming Language :: Python :: 3
Classifier: License :: OSI Approved :: MIT License
Classifier: Operating System :: OS Independent
